mynode_setup/__init__.py
mynode_setup/__main__.py
node_thunder-0.1.0.data/scripts/__main__.py
node_thunder-0.1.0.dist-info/METADATA
node_thunder-0.1.0.dist-info/WHEEL
node_thunder-0.1.0.dist-info/entry_points.txt
node_thunder-0.1.0.dist-info/top_level.txt
node_thunder-0.1.0.dist-info/RECORD
