Metadata-Version: 2.1
Name: node-thunder
Version: 0.1.0
Summary: A script to set up a basic Node.js project
Home-page: UNKNOWN
Author: Aradhya Pitlawar
Author-email: pitlawararadhya@gmail.com
License: UNKNOWN
Platform: UNKNOWN
Classifier: License :: OSI Approved :: MIT License
Classifier: Programming Language :: Python :: 3
Classifier: Programming Language :: Python :: 3.6
Classifier: Programming Language :: Python :: 3.7
Classifier: Programming Language :: Python :: 3.8
Classifier: Programming Language :: Python :: 3.9
